LICENSE
README.md
setup.py
DiffCD.egg-info/PKG-INFO
DiffCD.egg-info/SOURCES.txt
DiffCD.egg-info/dependency_links.txt
DiffCD.egg-info/requires.txt
DiffCD.egg-info/top_level.txt
diffcd/__init__.py
diffcd/diffcd
diffcd/main.py
diffcd/main_bak.py
diffcd/options.py