Metadata-Version: 2.4
Name: DiffCD
Version: 1.0.7
Summary: Content Discovery tool using response diffing for finding more interesting/hidden content on web applications.
Author: William Kristoffersen
Author-email: william.kristof@gmail.com
License-File: LICENSE
Requires-Dist: requests
Requires-Dist: httpdiff
Requires-Dist: httpinsert
Dynamic: author
Dynamic: author-email
Dynamic: description
Dynamic: description-content-type
Dynamic: license-file
Dynamic: requires-dist
Dynamic: summary
